{"build_time":"2026-05-26T19:01:56.635280Z","rows":[{"yb_etf":"AMYY","underlying":"AMD","option_root":"2AMDL","sleeve_2x":"AMDL","expiry":"2026-05-27","strike_long":47.89,"strike_short":50.55,"qty":940.0,"spot_2x":65.94,"moneyness_long_pct":-27.373,"moneyness_short_pct":-23.339,"iv_put_long":null,"iv_put_short":null,"spread_mid_market":null,"spread_mid_market_unavailable":true,"rv_30d_2x":1.714649,"rv_30d_underlying":null,"vrp_vol_2x":null,"rv_30d_source":"dashboard_1m","iv_source":"holdings_missing_chain","holdings_as_of":"2026-05-22","options_as_of":"2026-05-26T18:55:41.732979Z","days_to_exp":1,"iv_put_long_full":null,"iv_put_short_full":null,"iv_put_long_base":null,"iv_put_short_base":null,"iv_full_proxy":null,"iv_base_proxy":null,"rv_30d_2x_full":1.714649,"rv_30d_2x_base":1.548832,"vrp_vol_2x_full":null,"vrp_vol_2x_base":null,"event_implied_move_pct":null,"event_var_2x_annualized":null,"event_count_in_window":0,"event_types_in_window":[],"event_var_source":"none","event_calendar_stale":false,"put_spread_fair_event_aware":null,"put_spread_vrp_event_aware":null,"iv_underlying_implied":null,"iv_implied_weekly_move_2x_pct":24.1524,"iv_implied_weekly_move_underlying_pct":12.0762,"bs_put_spread_fair_diffusion":0.011381,"bs_put_spread_sigma_source":"rv_2x_full","expected_weekly_loss_pct_of_spot":0.0173,"spread_breakeven_sigma_annual":null,"iv_minus_breakeven_sigma":null,"bs_delta_spread":0.004653,"bs_gamma_spread":-0.00177103,"bs_vega_spread":-0.052396,"bs_theta_spread_per_day":0.044866,"bs_dollar_gamma_per_1pct_sleeve":-0.00077,"bs_dollar_gamma_per_1pct_underlying":-0.00308,"sleeve_diffusion_drag_annual":0.735005,"inverse_sleeve_drag_annual_x_minus2":2.205016},{"yb_etf":"AZYY","underlying":"AMZN","option_root":"2AMZZ","sleeve_2x":"AMZZ","expiry":"2026-05-27","strike_long":35.07,"strike_short":37.02,"qty":530.0,"spot_2x":38.285,"moneyness_long_pct":-8.398,"moneyness_short_pct":-3.304,"iv_put_long":null,"iv_put_short":null,"spread_mid_market":null,"spread_mid_market_unavailable":true,"rv_30d_2x":0.412296,"rv_30d_underlying":null,"vrp_vol_2x":null,"rv_30d_source":"dashboard_1m","iv_source":"holdings_missing_chain","holdings_as_of":"2026-05-22","options_as_of":"2026-05-26T18:55:41.732979Z","days_to_exp":1,"iv_put_long_full":null,"iv_put_short_full":null,"iv_put_long_base":null,"iv_put_short_base":null,"iv_full_proxy":null,"iv_base_proxy":null,"rv_30d_2x_full":0.412296,"rv_30d_2x_base":0.375191,"vrp_vol_2x_full":null,"vrp_vol_2x_base":null,"event_implied_move_pct":null,"event_var_2x_annualized":null,"event_count_in_window":0,"event_types_in_window":[],"event_var_source":"none","event_calendar_stale":false,"put_spread_fair_event_aware":null,"put_spread_vrp_event_aware":null,"iv_underlying_implied":null,"iv_implied_weekly_move_2x_pct":5.8076,"iv_implied_weekly_move_underlying_pct":2.9038,"bs_put_spread_fair_diffusion":0.044398,"bs_put_spread_sigma_source":"rv_2x_full","expected_weekly_loss_pct_of_spot":0.116,"spread_breakeven_sigma_annual":null,"iv_minus_breakeven_sigma":null,"bs_delta_spread":0.09421,"bs_gamma_spread":-0.1681337,"bs_vega_spread":-0.4032,"bs_theta_spread_per_day":0.082496,"bs_dollar_gamma_per_1pct_sleeve":-0.024644,"bs_dollar_gamma_per_1pct_underlying":-0.098576,"sleeve_diffusion_drag_annual":0.042497,"inverse_sleeve_drag_annual_x_minus2":0.127491},{"yb_etf":"BBYY","underlying":"BABA","option_root":"2BABX","sleeve_2x":"BABX","expiry":"2026-05-27","strike_long":24.57,"strike_short":25.94,"qty":180.0,"spot_2x":25.245,"moneyness_long_pct":-2.674,"moneyness_short_pct":2.753,"iv_put_long":null,"iv_put_short":null,"spread_mid_market":null,"spread_mid_market_unavailable":true,"rv_30d_2x":0.975362,"rv_30d_underlying":null,"vrp_vol_2x":null,"rv_30d_source":"dashboard_1m","iv_source":"holdings_missing_chain","holdings_as_of":"2026-05-22","options_as_of":"2026-05-26T18:55:41.732979Z","days_to_exp":1,"iv_put_long_full":null,"iv_put_short_full":null,"iv_put_long_base":null,"iv_put_short_base":null,"iv_full_proxy":null,"iv_base_proxy":null,"rv_30d_2x_full":0.975362,"rv_30d_2x_base":0.789245,"vrp_vol_2x_full":null,"vrp_vol_2x_base":null,"event_implied_move_pct":null,"event_var_2x_annualized":null,"event_count_in_window":0,"event_types_in_window":[],"event_var_source":"none","event_calendar_stale":false,"put_spread_fair_event_aware":null,"put_spread_vrp_event_aware":null,"iv_underlying_implied":null,"iv_implied_weekly_move_2x_pct":13.7389,"iv_implied_weekly_move_underlying_pct":6.8694,"bs_put_spread_fair_diffusion":0.70205,"bs_put_spread_sigma_source":"rv_2x_full","expected_weekly_loss_pct_of_spot":2.7809,"spread_breakeven_sigma_annual":null,"iv_minus_breakeven_sigma":null,"bs_delta_spread":0.341014,"bs_gamma_spread":-0.00680429,"bs_vega_spread":-0.016784,"bs_theta_spread_per_day":0.006597,"bs_dollar_gamma_per_1pct_sleeve":-0.000434,"bs_dollar_gamma_per_1pct_underlying":-0.001735,"sleeve_diffusion_drag_annual":0.237833,"inverse_sleeve_drag_annual_x_minus2":0.713498},{"yb_etf":"BIOY","underlying":"XBI","option_root":"2LABU","sleeve_2x":"LABU","expiry":"2026-05-26","strike_long":144.56,"strike_short":152.59,"qty":50.0,"spot_2x":180.725,"moneyness_long_pct":-20.011,"moneyness_short_pct":-15.568,"iv_put_long":null,"iv_put_short":null,"spread_mid_market":null,"spread_mid_market_unavailable":true,"rv_30d_2x":0.878903,"rv_30d_underlying":null,"vrp_vol_2x":null,"rv_30d_source":"dashboard_1m","iv_source":"holdings_missing_chain","holdings_as_of":"2026-05-22","options_as_of":"2026-05-26T18:55:41.732979Z","days_to_exp":0,"iv_put_long_full":null,"iv_put_short_full":null,"iv_put_long_base":null,"iv_put_short_base":null,"iv_full_proxy":null,"iv_base_proxy":null,"rv_30d_2x_full":0.878903,"rv_30d_2x_base":0.823904,"vrp_vol_2x_full":null,"vrp_vol_2x_base":null,"event_implied_move_pct":null,"event_var_2x_annualized":null,"event_count_in_window":0,"event_types_in_window":[],"event_var_source":"none","event_calendar_stale":false,"put_spread_fair_event_aware":null,"put_spread_vrp_event_aware":null,"iv_underlying_implied":null,"iv_implied_weekly_move_2x_pct":12.3801,"iv_implied_weekly_move_underlying_pct":6.1901,"bs_put_spread_fair_diffusion":0.002787,"bs_put_spread_sigma_source":"rv_2x_full","expected_weekly_loss_pct_of_spot":0.0015,"spread_breakeven_sigma_annual":null,"iv_minus_breakeven_sigma":null,"bs_delta_spread":0.000986,"bs_gamma_spread":-0.00032932,"bs_vega_spread":-0.037514,"bs_theta_spread_per_day":0.016455,"bs_dollar_gamma_per_1pct_sleeve":-0.001076,"bs_dollar_gamma_per_1pct_underlying":-0.004302,"sleeve_diffusion_drag_annual":0.193118,"inverse_sleeve_drag_annual_x_minus2":0.579353},{"yb_etf":"COYY","underlying":"COIN","option_root":"2CONL","sleeve_2x":"CONL","expiry":"2026-05-26","strike_long":6.89,"strike_short":7.27,"qty":9350.0,"spot_2x":6.93,"moneyness_long_pct":-0.577,"moneyness_short_pct":4.906,"iv_put_long":null,"iv_put_short":null,"spread_mid_market":null,"spread_mid_market_unavailable":true,"rv_30d_2x":1.32503,"rv_30d_underlying":null,"vrp_vol_2x":null,"rv_30d_source":"dashboard_1m","iv_source":"holdings_missing_chain","holdings_as_of":"2026-05-22","options_as_of":"2026-05-26T18:55:41.732979Z","days_to_exp":0,"iv_put_long_full":null,"iv_put_short_full":null,"iv_put_long_base":null,"iv_put_short_base":null,"iv_full_proxy":null,"iv_base_proxy":null,"rv_30d_2x_full":1.32503,"rv_30d_2x_base":1.09911,"vrp_vol_2x_full":null,"vrp_vol_2x_base":null,"event_implied_move_pct":null,"event_var_2x_annualized":null,"event_count_in_window":0,"event_types_in_window":[],"event_var_source":"none","event_calendar_stale":false,"put_spread_fair_event_aware":null,"put_spread_vrp_event_aware":null,"iv_underlying_implied":null,"iv_implied_weekly_move_2x_pct":18.6642,"iv_implied_weekly_move_underlying_pct":9.3321,"bs_put_spread_fair_diffusion":0.233289,"bs_put_spread_sigma_source":"rv_2x_full","expected_weekly_loss_pct_of_spot":3.3664,"spread_breakeven_sigma_annual":null,"iv_minus_breakeven_sigma":null,"bs_delta_spread":0.246996,"bs_gamma_spread":0.08598627,"bs_vega_spread":0.021713,"bs_theta_spread_per_day":-0.014717,"bs_dollar_gamma_per_1pct_sleeve":0.000413,"bs_dollar_gamma_per_1pct_underlying":0.001652,"sleeve_diffusion_drag_annual":0.438926,"inverse_sleeve_drag_annual_x_minus2":1.316778},{"yb_etf":"CRY","underlying":"CRCL","option_root":"2CRCA","sleeve_2x":"CRCA","expiry":"2026-05-26","strike_long":42.91,"strike_short":45.3,"qty":180.0,"spot_2x":42.07,"moneyness_long_pct":1.997,"moneyness_short_pct":7.678,"iv_put_long":null,"iv_put_short":null,"spread_mid_market":null,"spread_mid_market_unavailable":true,"rv_30d_2x":2.169601,"rv_30d_underlying":null,"vrp_vol_2x":null,"rv_30d_source":"dashboard_1m","iv_source":"holdings_missing_chain","holdings_as_of":"2026-05-22","options_as_of":"2026-05-26T18:55:41.732979Z","days_to_exp":0,"iv_put_long_full":null,"iv_put_short_full":null,"iv_put_long_base":null,"iv_put_short_base":null,"iv_full_proxy":null,"iv_base_proxy":null,"rv_30d_2x_full":2.169601,"rv_30d_2x_base":1.652317,"vrp_vol_2x_full":null,"vrp_vol_2x_base":null,"event_implied_move_pct":null,"event_var_2x_annualized":null,"event_count_in_window":0,"event_types_in_window":[],"event_var_source":"none","event_calendar_stale":false,"put_spread_fair_event_aware":null,"put_spread_vrp_event_aware":null,"iv_underlying_implied":null,"iv_implied_weekly_move_2x_pct":30.5608,"iv_implied_weekly_move_underlying_pct":15.2804,"bs_put_spread_fair_diffusion":1.574225,"bs_put_spread_sigma_source":"rv_2x_full","expected_weekly_loss_pct_of_spot":3.7419,"spread_breakeven_sigma_annual":null,"iv_minus_breakeven_sigma":null,"bs_delta_spread":0.151493,"bs_gamma_spread":0.00710852,"bs_vega_spread":0.108319,"bs_theta_spread_per_day":-0.11886,"bs_dollar_gamma_per_1pct_sleeve":0.001258,"bs_dollar_gamma_per_1pct_underlying":0.005033,"sleeve_diffusion_drag_annual":1.176792,"inverse_sleeve_drag_annual_x_minus2":3.530376},{"yb_etf":"CWY","underlying":"CRWV","option_root":"2CWVX","sleeve_2x":"CRWV","expiry":"2026-05-26","strike_long":27.89,"strike_short":29.44,"qty":240.0,"spot_2x":105.58,"moneyness_long_pct":-73.584,"moneyness_short_pct":-72.116,"iv_put_long":null,"iv_put_short":null,"spread_mid_market":null,"spread_mid_market_unavailable":true,"rv_30d_2x":null,"rv_30d_underlying":null,"vrp_vol_2x":null,"rv_30d_source":null,"iv_source":"holdings_missing_chain","holdings_as_of":"2026-05-22","options_as_of":"2026-05-26T18:55:41.732979Z","days_to_exp":0,"iv_put_long_full":null,"iv_put_short_full":null,"iv_put_long_base":null,"iv_put_short_base":null,"iv_full_proxy":null,"iv_base_proxy":null,"rv_30d_2x_full":null,"rv_30d_2x_base":null,"vrp_vol_2x_full":null,"vrp_vol_2x_base":null,"event_implied_move_pct":null,"event_var_2x_annualized":null,"event_count_in_window":0,"event_types_in_window":[],"event_var_source":"none","event_calendar_stale":false,"put_spread_fair_event_aware":null,"put_spread_vrp_event_aware":null,"iv_underlying_implied":null,"iv_implied_weekly_move_2x_pct":null,"iv_implied_weekly_move_underlying_pct":null,"bs_put_spread_fair_diffusion":null,"bs_put_spread_sigma_source":null,"expected_weekly_loss_pct_of_spot":null,"spread_breakeven_sigma_annual":null,"iv_minus_breakeven_sigma":null,"bs_delta_spread":null,"bs_gamma_spread":null,"bs_vega_spread":null,"bs_theta_spread_per_day":null,"bs_dollar_gamma_per_1pct_sleeve":null,"bs_dollar_gamma_per_1pct_underlying":null,"sleeve_diffusion_drag_annual":null,"inverse_sleeve_drag_annual_x_minus2":null},{"yb_etf":"FBYY","underlying":"META","option_root":"2FBL","sleeve_2x":"FBL","expiry":"2026-05-26","strike_long":22.85,"strike_short":24.12,"qty":40.0,"spot_2x":25.215,"moneyness_long_pct":-9.379,"moneyness_short_pct":-4.343,"iv_put_long":null,"iv_put_short":null,"spread_mid_market":null,"spread_mid_market_unavailable":true,"rv_30d_2x":0.735412,"rv_30d_underlying":null,"vrp_vol_2x":null,"rv_30d_source":"dashboard_1m","iv_source":"holdings_missing_chain","holdings_as_of":"2026-05-22","options_as_of":"2026-05-26T18:55:41.732979Z","days_to_exp":0,"iv_put_long_full":null,"iv_put_short_full":null,"iv_put_long_base":null,"iv_put_short_base":null,"iv_full_proxy":null,"iv_base_proxy":null,"rv_30d_2x_full":0.735412,"rv_30d_2x_base":0.341597,"vrp_vol_2x_full":null,"vrp_vol_2x_base":null,"event_implied_move_pct":null,"event_var_2x_annualized":null,"event_count_in_window":0,"event_types_in_window":[],"event_var_source":"none","event_calendar_stale":false,"put_spread_fair_event_aware":null,"put_spread_vrp_event_aware":null,"iv_underlying_implied":null,"iv_implied_weekly_move_2x_pct":10.3589,"iv_implied_weekly_move_underlying_pct":5.1795,"bs_put_spread_fair_diffusion":0.095618,"bs_put_spread_sigma_source":"rv_2x_full","expected_weekly_loss_pct_of_spot":0.3792,"spread_breakeven_sigma_annual":null,"iv_minus_breakeven_sigma":null,"bs_delta_spread":0.146593,"bs_gamma_spread":-0.17655334,"bs_vega_spread":-0.327585,"bs_theta_spread_per_day":0.119808,"bs_dollar_gamma_per_1pct_sleeve":-0.011225,"bs_dollar_gamma_per_1pct_underlying":-0.044901,"sleeve_diffusion_drag_annual":0.135208,"inverse_sleeve_drag_annual_x_minus2":0.405623},{"yb_etf":"FINY","underlying":"XLF","option_root":"2FAS","sleeve_2x":"FAS","expiry":"2026-05-26","strike_long":120.31,"strike_short":127.0,"qty":60.0,"spot_2x":134.03,"moneyness_long_pct":-10.237,"moneyness_short_pct":-5.245,"iv_put_long":null,"iv_put_short":null,"spread_mid_market":null,"spread_mid_market_unavailable":true,"rv_30d_2x":null,"rv_30d_underlying":null,"vrp_vol_2x":null,"rv_30d_source":null,"iv_source":"holdings_missing_chain","holdings_as_of":"2026-05-22","options_as_of":"2026-05-26T18:55:41.732979Z","days_to_exp":0,"iv_put_long_full":null,"iv_put_short_full":null,"iv_put_long_base":null,"iv_put_short_base":null,"iv_full_proxy":null,"iv_base_proxy":null,"rv_30d_2x_full":null,"rv_30d_2x_base":null,"vrp_vol_2x_full":null,"vrp_vol_2x_base":null,"event_implied_move_pct":null,"event_var_2x_annualized":null,"event_count_in_window":0,"event_types_in_window":[],"event_var_source":"none","event_calendar_stale":false,"put_spread_fair_event_aware":null,"put_spread_vrp_event_aware":null,"iv_underlying_implied":null,"iv_implied_weekly_move_2x_pct":null,"iv_implied_weekly_move_underlying_pct":null,"bs_put_spread_fair_diffusion":null,"bs_put_spread_sigma_source":null,"expected_weekly_loss_pct_of_spot":null,"spread_breakeven_sigma_annual":null,"iv_minus_breakeven_sigma":null,"bs_delta_spread":null,"bs_gamma_spread":null,"bs_vega_spread":null,"bs_theta_spread_per_day":null,"bs_dollar_gamma_per_1pct_sleeve":null,"bs_dollar_gamma_per_1pct_underlying":null,"sleeve_diffusion_drag_annual":null,"inverse_sleeve_drag_annual_x_minus2":null},{"yb_etf":"FIYY","underlying":"TLT","option_root":"2TMF","sleeve_2x":"TMF","expiry":"2026-05-26","strike_long":29.27,"strike_short":30.89,"qty":240.0,"spot_2x":34.08,"moneyness_long_pct":-14.114,"moneyness_short_pct":-9.36,"iv_put_long":null,"iv_put_short":null,"spread_mid_market":null,"spread_mid_market_unavailable":true,"rv_30d_2x":null,"rv_30d_underlying":null,"vrp_vol_2x":null,"rv_30d_source":null,"iv_source":"holdings_missing_chain","holdings_as_of":"2026-05-22","options_as_of":"2026-05-26T17:44:11.755291Z","days_to_exp":0,"iv_put_long_full":null,"iv_put_short_full":null,"iv_put_long_base":null,"iv_put_short_base":null,"iv_full_proxy":null,"iv_base_proxy":null,"rv_30d_2x_full":null,"rv_30d_2x_base":null,"vrp_vol_2x_full":null,"vrp_vol_2x_base":null,"event_implied_move_pct":null,"event_var_2x_annualized":null,"event_count_in_window":0,"event_types_in_window":[],"event_var_source":"none","event_calendar_stale":false,"put_spread_fair_event_aware":null,"put_spread_vrp_event_aware":null,"iv_underlying_implied":null,"iv_implied_weekly_move_2x_pct":null,"iv_implied_weekly_move_underlying_pct":null,"bs_put_spread_fair_diffusion":null,"bs_put_spread_sigma_source":null,"expected_weekly_loss_pct_of_spot":null,"spread_breakeven_sigma_annual":null,"iv_minus_breakeven_sigma":null,"bs_delta_spread":null,"bs_gamma_spread":null,"bs_vega_spread":null,"bs_theta_spread_per_day":null,"bs_dollar_gamma_per_1pct_sleeve":null,"bs_dollar_gamma_per_1pct_underlying":null,"sleeve_diffusion_drag_annual":null,"inverse_sleeve_drag_annual_x_minus2":null},{"yb_etf":"HMYY","underlying":"HIMS","option_root":"2HIMZ","sleeve_2x":"HIMZ","expiry":"2026-05-26","strike_long":20.2,"strike_short":21.32,"qty":90.0,"spot_2x":24.52,"moneyness_long_pct":-17.618,"moneyness_short_pct":-13.051,"iv_put_long":null,"iv_put_short":null,"spread_mid_market":null,"spread_mid_market_unavailable":true,"rv_30d_2x":1.870134,"rv_30d_underlying":null,"vrp_vol_2x":null,"rv_30d_source":"dashboard_1m","iv_source":"holdings_missing_chain","holdings_as_of":"2026-05-22","options_as_of":"2026-05-26T18:55:41.732979Z","days_to_exp":0,"iv_put_long_full":null,"iv_put_short_full":null,"iv_put_long_base":null,"iv_put_short_base":null,"iv_full_proxy":null,"iv_base_proxy":null,"rv_30d_2x_full":1.870134,"rv_30d_2x_base":1.751043,"vrp_vol_2x_full":null,"vrp_vol_2x_base":null,"event_implied_move_pct":null,"event_var_2x_annualized":null,"event_count_in_window":0,"event_types_in_window":[],"event_var_source":"none","event_calendar_stale":false,"put_spread_fair_event_aware":null,"put_spread_vrp_event_aware":null,"iv_underlying_implied":null,"iv_implied_weekly_move_2x_pct":26.3425,"iv_implied_weekly_move_underlying_pct":13.1713,"bs_put_spread_fair_diffusion":0.100041,"bs_put_spread_sigma_source":"rv_2x_full","expected_weekly_loss_pct_of_spot":0.408,"spread_breakeven_sigma_annual":null,"iv_minus_breakeven_sigma":null,"bs_delta_spread":0.062071,"bs_gamma_spread":-0.03117878,"bs_vega_spread":-0.139114,"bs_theta_spread_per_day":0.129805,"bs_dollar_gamma_per_1pct_sleeve":-0.001875,"bs_dollar_gamma_per_1pct_underlying":-0.007498,"sleeve_diffusion_drag_annual":0.87435,"inverse_sleeve_drag_annual_x_minus2":2.623051},{"yb_etf":"HOYY","underlying":"HOOD","option_root":"2ROBN","sleeve_2x":"ROBN","expiry":"2026-05-26","strike_long":17.51,"strike_short":18.49,"qty":779.0,"spot_2x":17.755,"moneyness_long_pct":-1.38,"moneyness_short_pct":4.14,"iv_put_long":null,"iv_put_short":null,"spread_mid_market":null,"spread_mid_market_unavailable":true,"rv_30d_2x":1.423995,"rv_30d_underlying":null,"vrp_vol_2x":null,"rv_30d_source":"dashboard_1m","iv_source":"holdings_missing_chain","holdings_as_of":"2026-05-22","options_as_of":"2026-05-26T17:44:11.755291Z","days_to_exp":0,"iv_put_long_full":null,"iv_put_short_full":null,"iv_put_long_base":null,"iv_put_short_base":null,"iv_full_proxy":null,"iv_base_proxy":null,"rv_30d_2x_full":1.423995,"rv_30d_2x_base":1.014574,"vrp_vol_2x_full":null,"vrp_vol_2x_base":null,"event_implied_move_pct":null,"event_var_2x_annualized":null,"event_count_in_window":0,"event_types_in_window":[],"event_var_source":"none","event_calendar_stale":false,"put_spread_fair_event_aware":null,"put_spread_vrp_event_aware":null,"iv_underlying_implied":null,"iv_implied_weekly_move_2x_pct":20.0583,"iv_implied_weekly_move_underlying_pct":10.0291,"bs_put_spread_fair_diffusion":0.564288,"bs_put_spread_sigma_source":"rv_2x_full","expected_weekly_loss_pct_of_spot":3.1782,"spread_breakeven_sigma_annual":null,"iv_minus_breakeven_sigma":null,"bs_delta_spread":0.237328,"bs_gamma_spread":0.01472234,"bs_vega_spread":0.026226,"bs_theta_spread_per_day":-0.019488,"bs_dollar_gamma_per_1pct_sleeve":0.000464,"bs_dollar_gamma_per_1pct_underlying":0.001856,"sleeve_diffusion_drag_annual":0.50694,"inverse_sleeve_drag_annual_x_minus2":1.520821},{"yb_etf":"IOYY","underlying":"IONQ","option_root":"2IONL","sleeve_2x":"IONL","expiry":"2026-05-26","strike_long":24.07,"strike_short":25.4,"qty":590.0,"spot_2x":42.4,"moneyness_long_pct":-43.231,"moneyness_short_pct":-40.094,"iv_put_long":null,"iv_put_short":null,"spread_mid_market":null,"spread_mid_market_unavailable":true,"rv_30d_2x":2.056596,"rv_30d_underlying":null,"vrp_vol_2x":null,"rv_30d_source":"dashboard_1m","iv_source":"holdings_missing_chain","holdings_as_of":"2026-05-22","options_as_of":"2026-05-26T18:55:41.732979Z","days_to_exp":0,"iv_put_long_full":null,"iv_put_short_full":null,"iv_put_long_base":null,"iv_put_short_base":null,"iv_full_proxy":null,"iv_base_proxy":null,"rv_30d_2x_full":2.056596,"rv_30d_2x_base":1.82861,"vrp_vol_2x_full":null,"vrp_vol_2x_base":null,"event_implied_move_pct":null,"event_var_2x_annualized":null,"event_count_in_window":0,"event_types_in_window":[],"event_var_source":"none","event_calendar_stale":false,"put_spread_fair_event_aware":null,"put_spread_vrp_event_aware":null,"iv_underlying_implied":null,"iv_implied_weekly_move_2x_pct":28.969,"iv_implied_weekly_move_underlying_pct":14.4845,"bs_put_spread_fair_diffusion":3.1e-05,"bs_put_spread_sigma_source":"rv_2x_full","expected_weekly_loss_pct_of_spot":0.0001,"spread_breakeven_sigma_annual":null,"iv_minus_breakeven_sigma":null,"bs_delta_spread":2.4e-05,"bs_gamma_spread":-1.851e-05,"bs_vega_spread":-0.000272,"bs_theta_spread_per_day":0.000279,"bs_dollar_gamma_per_1pct_sleeve":-3e-06,"bs_dollar_gamma_per_1pct_underlying":-1.3e-05,"sleeve_diffusion_drag_annual":1.057397,"inverse_sleeve_drag_annual_x_minus2":3.17219},{"yb_etf":"MAAY","underlying":"MARA","option_root":"2MRAL","sleeve_2x":"MRAL","expiry":"2026-05-26","strike_long":53.07,"strike_short":56.02,"qty":140.0,"spot_2x":79.04,"moneyness_long_pct":-32.857,"moneyness_short_pct":-29.124,"iv_put_long":null,"iv_put_short":null,"spread_mid_market":null,"spread_mid_market_unavailable":true,"rv_30d_2x":1.370586,"rv_30d_underlying":null,"vrp_vol_2x":null,"rv_30d_source":"dashboard_1m","iv_source":"holdings_missing_chain","holdings_as_of":"2026-05-22","options_as_of":"2026-05-26T18:55:41.732979Z","days_to_exp":0,"iv_put_long_full":null,"iv_put_short_full":null,"iv_put_long_base":null,"iv_put_short_base":null,"iv_full_proxy":null,"iv_base_proxy":null,"rv_30d_2x_full":1.370586,"rv_30d_2x_base":1.148921,"vrp_vol_2x_full":null,"vrp_vol_2x_base":null,"event_implied_move_pct":null,"event_var_2x_annualized":null,"event_count_in_window":0,"event_types_in_window":[],"event_var_source":"none","event_calendar_stale":false,"put_spread_fair_event_aware":null,"put_spread_vrp_event_aware":null,"iv_underlying_implied":null,"iv_implied_weekly_move_2x_pct":19.3059,"iv_implied_weekly_move_underlying_pct":9.653,"bs_put_spread_fair_diffusion":4.1e-05,"bs_put_spread_sigma_source":"rv_2x_full","expected_weekly_loss_pct_of_spot":0.0001,"spread_breakeven_sigma_annual":null,"iv_minus_breakeven_sigma":null,"bs_delta_spread":2.6e-05,"bs_gamma_spread":-1.609e-05,"bs_vega_spread":-0.000547,"bs_theta_spread_per_day":0.000374,"bs_dollar_gamma_per_1pct_sleeve":-1e-05,"bs_dollar_gamma_per_1pct_underlying":-4e-05,"sleeve_diffusion_drag_annual":0.469626,"inverse_sleeve_drag_annual_x_minus2":1.408879},{"yb_etf":"MTYY","underlying":"MSTR","option_root":"2MSTU","sleeve_2x":"MSTU","expiry":"2026-05-26","strike_long":6.16,"strike_short":6.5,"qty":840.0,"spot_2x":6.2399,"moneyness_long_pct":-1.28,"moneyness_short_pct":4.168,"iv_put_long":null,"iv_put_short":null,"spread_mid_market":null,"spread_mid_market_unavailable":true,"rv_30d_2x":1.272395,"rv_30d_underlying":null,"vrp_vol_2x":null,"rv_30d_source":"dashboard_1m","iv_source":"holdings_missing_chain","holdings_as_of":"2026-05-22","options_as_of":"2026-05-26T18:55:41.732979Z","days_to_exp":0,"iv_put_long_full":null,"iv_put_short_full":null,"iv_put_long_base":null,"iv_put_short_base":null,"iv_full_proxy":null,"iv_base_proxy":null,"rv_30d_2x_full":1.272395,"rv_30d_2x_base":1.077128,"vrp_vol_2x_full":null,"vrp_vol_2x_base":null,"event_implied_move_pct":null,"event_var_2x_annualized":null,"event_count_in_window":0,"event_types_in_window":[],"event_var_source":"none","event_calendar_stale":false,"put_spread_fair_event_aware":null,"put_spread_vrp_event_aware":null,"iv_underlying_implied":null,"iv_implied_weekly_move_2x_pct":17.9228,"iv_implied_weekly_move_underlying_pct":8.9614,"bs_put_spread_fair_diffusion":0.198424,"bs_put_spread_sigma_source":"rv_2x_full","expected_weekly_loss_pct_of_spot":3.1799,"spread_breakeven_sigma_annual":null,"iv_minus_breakeven_sigma":null,"bs_delta_spread":0.260283,"bs_gamma_spread":0.06623712,"bs_vega_spread":0.013022,"bs_theta_spread_per_day":-0.008596,"bs_dollar_gamma_per_1pct_sleeve":0.000258,"bs_dollar_gamma_per_1pct_underlying":0.001032,"sleeve_diffusion_drag_annual":0.404747,"inverse_sleeve_drag_annual_x_minus2":1.214242},{"yb_etf":"MUYY","underlying":"MU","option_root":"2MULL","sleeve_2x":"MULL","expiry":"2026-05-26","strike_long":348.38,"strike_short":384.84,"qty":40.0,"spot_2x":661.425,"moneyness_long_pct":-47.329,"moneyness_short_pct":-41.817,"iv_put_long":null,"iv_put_short":null,"spread_mid_market":null,"spread_mid_market_unavailable":true,"rv_30d_2x":2.022586,"rv_30d_underlying":null,"vrp_vol_2x":null,"rv_30d_source":"dashboard_1m","iv_source":"holdings_missing_chain","holdings_as_of":"2026-05-22","options_as_of":"2026-05-26T18:55:41.732979Z","days_to_exp":0,"iv_put_long_full":null,"iv_put_short_full":null,"iv_put_long_base":null,"iv_put_short_base":null,"iv_full_proxy":null,"iv_base_proxy":null,"rv_30d_2x_full":2.022586,"rv_30d_2x_base":2.035843,"vrp_vol_2x_full":null,"vrp_vol_2x_base":null,"event_implied_move_pct":null,"event_var_2x_annualized":null,"event_count_in_window":0,"event_types_in_window":[],"event_var_source":"none","event_calendar_stale":false,"put_spread_fair_event_aware":null,"put_spread_vrp_event_aware":null,"iv_underlying_implied":null,"iv_implied_weekly_move_2x_pct":28.49,"iv_implied_weekly_move_underlying_pct":14.245,"bs_put_spread_fair_diffusion":0.000143,"bs_put_spread_sigma_source":"rv_2x_full","expected_weekly_loss_pct_of_spot":0.0,"spread_breakeven_sigma_annual":null,"iv_minus_breakeven_sigma":null,"bs_delta_spread":8e-06,"bs_gamma_spread":-4.2e-07,"bs_vega_spread":-0.001463,"bs_theta_spread_per_day":0.001479,"bs_dollar_gamma_per_1pct_sleeve":-1.8e-05,"bs_dollar_gamma_per_1pct_underlying":-7.3e-05,"sleeve_diffusion_drag_annual":1.022714,"inverse_sleeve_drag_annual_x_minus2":3.068141},{"yb_etf":"NUGY","underlying":"GDX","option_root":"2NUGT","sleeve_2x":"NUGT","expiry":"2026-05-26","strike_long":147.08,"strike_short":155.25,"qty":250.0,"spot_2x":165.68,"moneyness_long_pct":-11.226,"moneyness_short_pct":-6.295,"iv_put_long":null,"iv_put_short":null,"spread_mid_market":null,"spread_mid_market_unavailable":true,"rv_30d_2x":1.056695,"rv_30d_underlying":null,"vrp_vol_2x":null,"rv_30d_source":"dashboard_1m","iv_source":"holdings_missing_chain","holdings_as_of":"2026-05-22","options_as_of":"2026-05-26T18:55:41.732979Z","days_to_exp":0,"iv_put_long_full":null,"iv_put_short_full":null,"iv_put_long_base":null,"iv_put_short_base":null,"iv_full_proxy":null,"iv_base_proxy":null,"rv_30d_2x_full":1.056695,"rv_30d_2x_base":1.168133,"vrp_vol_2x_full":null,"vrp_vol_2x_base":null,"event_implied_move_pct":null,"event_var_2x_annualized":null,"event_count_in_window":0,"event_types_in_window":[],"event_var_source":"none","event_calendar_stale":false,"put_spread_fair_event_aware":null,"put_spread_vrp_event_aware":null,"iv_underlying_implied":null,"iv_implied_weekly_move_2x_pct":14.8845,"iv_implied_weekly_move_underlying_pct":7.4423,"bs_put_spread_fair_diffusion":0.773092,"bs_put_spread_sigma_source":"rv_2x_full","expected_weekly_loss_pct_of_spot":0.4666,"spread_breakeven_sigma_annual":null,"iv_minus_breakeven_sigma":null,"bs_delta_spread":0.121597,"bs_gamma_spread":-0.01481854,"bs_vega_spread":-1.705669,"bs_theta_spread_per_day":0.897617,"bs_dollar_gamma_per_1pct_sleeve":-0.040677,"bs_dollar_gamma_per_1pct_underlying":-0.162707,"sleeve_diffusion_drag_annual":0.279151,"inverse_sleeve_drag_annual_x_minus2":0.837453},{"yb_etf":"NVYY","underlying":"NVDA","option_root":"2NVDL","sleeve_2x":"NVDL","expiry":"2026-05-26","strike_long":102.9,"strike_short":108.61,"qty":1680.0,"spot_2x":105.025,"moneyness_long_pct":-2.023,"moneyness_short_pct":3.413,"iv_put_long":null,"iv_put_short":null,"spread_mid_market":null,"spread_mid_market_unavailable":true,"rv_30d_2x":0.820827,"rv_30d_underlying":null,"vrp_vol_2x":null,"rv_30d_source":"dashboard_1m","iv_source":"holdings_missing_chain","holdings_as_of":"2026-05-22","options_as_of":"2026-05-26T18:55:41.732979Z","days_to_exp":0,"iv_put_long_full":null,"iv_put_short_full":null,"iv_put_long_base":null,"iv_put_short_base":null,"iv_full_proxy":null,"iv_base_proxy":null,"rv_30d_2x_full":0.820827,"rv_30d_2x_base":0.703596,"vrp_vol_2x_full":null,"vrp_vol_2x_base":null,"event_implied_move_pct":null,"event_var_2x_annualized":null,"event_count_in_window":0,"event_types_in_window":[],"event_var_source":"none","event_calendar_stale":false,"put_spread_fair_event_aware":null,"put_spread_vrp_event_aware":null,"iv_underlying_implied":null,"iv_implied_weekly_move_2x_pct":11.5621,"iv_implied_weekly_move_underlying_pct":5.781,"bs_put_spread_fair_diffusion":3.189274,"bs_put_spread_sigma_source":"rv_2x_full","expected_weekly_loss_pct_of_spot":3.0367,"spread_breakeven_sigma_annual":null,"iv_minus_breakeven_sigma":null,"bs_delta_spread":0.396754,"bs_gamma_spread":0.00651616,"bs_vega_spread":0.234114,"bs_theta_spread_per_day":-0.103738,"bs_dollar_gamma_per_1pct_sleeve":0.007187,"bs_dollar_gamma_per_1pct_underlying":0.02875,"sleeve_diffusion_drag_annual":0.168439,"inverse_sleeve_drag_annual_x_minus2":0.505318},{"yb_etf":"PLYY","underlying":"PLTR","option_root":"2PTIR","sleeve_2x":"PTIR","expiry":"2026-05-27","strike_long":12.35,"strike_short":13.03,"qty":1660.0,"spot_2x":13.58,"moneyness_long_pct":-9.057,"moneyness_short_pct":-4.05,"iv_put_long":null,"iv_put_short":null,"spread_mid_market":null,"spread_mid_market_unavailable":true,"rv_30d_2x":0.791097,"rv_30d_underlying":null,"vrp_vol_2x":null,"rv_30d_source":"dashboard_1m","iv_source":"holdings_missing_chain","holdings_as_of":"2026-05-22","options_as_of":"2026-05-26T18:55:41.732979Z","days_to_exp":1,"iv_put_long_full":null,"iv_put_short_full":null,"iv_put_long_base":null,"iv_put_short_base":null,"iv_full_proxy":null,"iv_base_proxy":null,"rv_30d_2x_full":0.791097,"rv_30d_2x_base":0.567709,"vrp_vol_2x_full":null,"vrp_vol_2x_base":null,"event_implied_move_pct":null,"event_var_2x_annualized":null,"event_count_in_window":0,"event_types_in_window":[],"event_var_source":"none","event_calendar_stale":false,"put_spread_fair_event_aware":null,"put_spread_vrp_event_aware":null,"iv_underlying_implied":null,"iv_implied_weekly_move_2x_pct":11.1433,"iv_implied_weekly_move_underlying_pct":5.5717,"bs_put_spread_fair_diffusion":0.068154,"bs_put_spread_sigma_source":"rv_2x_full","expected_weekly_loss_pct_of_spot":0.5019,"spread_breakeven_sigma_annual":null,"iv_minus_breakeven_sigma":null,"bs_delta_spread":0.168869,"bs_gamma_spread":-0.31705122,"bs_vega_spread":-0.183552,"bs_theta_spread_per_day":0.072201,"bs_dollar_gamma_per_1pct_sleeve":-0.005847,"bs_dollar_gamma_per_1pct_underlying":-0.023388,"sleeve_diffusion_drag_annual":0.156459,"inverse_sleeve_drag_annual_x_minus2":0.469376},{"yb_etf":"QBY","underlying":"QBTS","option_root":"2QBTX","sleeve_2x":"QBTX","expiry":"2026-05-26","strike_long":10.5,"strike_short":11.09,"qty":820.0,"spot_2x":21.945,"moneyness_long_pct":-52.153,"moneyness_short_pct":-49.465,"iv_put_long":null,"iv_put_short":null,"spread_mid_market":null,"spread_mid_market_unavailable":true,"rv_30d_2x":2.714739,"rv_30d_underlying":null,"vrp_vol_2x":null,"rv_30d_source":"dashboard_1m","iv_source":"holdings_missing_chain","holdings_as_of":"2026-05-22","options_as_of":"2026-05-26T18:55:41.732979Z","days_to_exp":0,"iv_put_long_full":null,"iv_put_short_full":null,"iv_put_long_base":null,"iv_put_short_base":null,"iv_full_proxy":null,"iv_base_proxy":null,"rv_30d_2x_full":2.714739,"rv_30d_2x_base":2.643497,"vrp_vol_2x_full":null,"vrp_vol_2x_base":null,"event_implied_move_pct":null,"event_var_2x_annualized":null,"event_count_in_window":0,"event_types_in_window":[],"event_var_source":"none","event_calendar_stale":false,"put_spread_fair_event_aware":null,"put_spread_vrp_event_aware":null,"iv_underlying_implied":null,"iv_implied_weekly_move_2x_pct":38.2396,"iv_implied_weekly_move_underlying_pct":19.1198,"bs_put_spread_fair_diffusion":1.5e-05,"bs_put_spread_sigma_source":"rv_2x_full","expected_weekly_loss_pct_of_spot":0.0001,"spread_breakeven_sigma_annual":null,"iv_minus_breakeven_sigma":null,"bs_delta_spread":1.7e-05,"bs_gamma_spread":-1.935e-05,"bs_vega_spread":-0.0001,"bs_theta_spread_per_day":0.000136,"bs_dollar_gamma_per_1pct_sleeve":-1e-06,"bs_dollar_gamma_per_1pct_underlying":-4e-06,"sleeve_diffusion_drag_annual":1.842452,"inverse_sleeve_drag_annual_x_minus2":5.527356},{"yb_etf":"RGYY","underlying":"RGTI","option_root":"2RGTX","sleeve_2x":"RGTX","expiry":"2026-05-27","strike_long":16.27,"strike_short":27.65,"qty":100.0,"spot_2x":35.535,"moneyness_long_pct":-54.214,"moneyness_short_pct":-22.189,"iv_put_long":null,"iv_put_short":null,"spread_mid_market":null,"spread_mid_market_unavailable":true,"rv_30d_2x":2.757307,"rv_30d_underlying":null,"vrp_vol_2x":null,"rv_30d_source":"dashboard_1m","iv_source":"holdings_missing_chain","holdings_as_of":"2026-05-22","options_as_of":"2026-05-26T17:44:11.755291Z","days_to_exp":1,"iv_put_long_full":null,"iv_put_short_full":null,"iv_put_long_base":null,"iv_put_short_base":null,"iv_full_proxy":null,"iv_base_proxy":null,"rv_30d_2x_full":2.757307,"rv_30d_2x_base":2.673218,"vrp_vol_2x_full":null,"vrp_vol_2x_base":null,"event_implied_move_pct":null,"event_var_2x_annualized":null,"event_count_in_window":0,"event_types_in_window":[],"event_var_source":"none","event_calendar_stale":false,"put_spread_fair_event_aware":null,"put_spread_vrp_event_aware":null,"iv_underlying_implied":null,"iv_implied_weekly_move_2x_pct":38.8392,"iv_implied_weekly_move_underlying_pct":19.4196,"bs_put_spread_fair_diffusion":0.179984,"bs_put_spread_sigma_source":"rv_2x_full","expected_weekly_loss_pct_of_spot":0.5065,"spread_breakeven_sigma_annual":null,"iv_minus_breakeven_sigma":null,"bs_delta_spread":0.062724,"bs_gamma_spread":-0.01997996,"bs_vega_spread":-0.276053,"bs_theta_spread_per_day":0.38017,"bs_dollar_gamma_per_1pct_sleeve":-0.002523,"bs_dollar_gamma_per_1pct_underlying":-0.010092,"sleeve_diffusion_drag_annual":1.900685,"inverse_sleeve_drag_annual_x_minus2":5.702056},{"yb_etf":"RTYY","underlying":"RIOT","option_root":"2RIOX","sleeve_2x":"RIOX","expiry":"2026-05-27","strike_long":43.16,"strike_short":45.55,"qty":650.0,"spot_2x":57.964,"moneyness_long_pct":-25.54,"moneyness_short_pct":-21.417,"iv_put_long":null,"iv_put_short":null,"spread_mid_market":null,"spread_mid_market_unavailable":true,"rv_30d_2x":1.765795,"rv_30d_underlying":null,"vrp_vol_2x":null,"rv_30d_source":"dashboard_1m","iv_source":"holdings_missing_chain","holdings_as_of":"2026-05-22","options_as_of":"2026-05-26T17:44:11.755291Z","days_to_exp":1,"iv_put_long_full":null,"iv_put_short_full":null,"iv_put_long_base":null,"iv_put_short_base":null,"iv_full_proxy":null,"iv_base_proxy":null,"rv_30d_2x_full":1.765795,"rv_30d_2x_base":2.243713,"vrp_vol_2x_full":null,"vrp_vol_2x_base":null,"event_implied_move_pct":null,"event_var_2x_annualized":null,"event_count_in_window":0,"event_types_in_window":[],"event_var_source":"none","event_calendar_stale":false,"put_spread_fair_event_aware":null,"put_spread_vrp_event_aware":null,"iv_underlying_implied":null,"iv_implied_weekly_move_2x_pct":24.8728,"iv_implied_weekly_move_underlying_pct":12.4364,"bs_put_spread_fair_diffusion":0.023654,"bs_put_spread_sigma_source":"rv_2x_full","expected_weekly_loss_pct_of_spot":0.0408,"spread_breakeven_sigma_annual":null,"iv_minus_breakeven_sigma":null,"bs_delta_spread":0.009699,"bs_gamma_spread":-0.00363924,"bs_vega_spread":-0.085678,"bs_theta_spread_per_day":0.075545,"bs_dollar_gamma_per_1pct_sleeve":-0.001223,"bs_dollar_gamma_per_1pct_underlying":-0.004891,"sleeve_diffusion_drag_annual":0.779508,"inverse_sleeve_drag_annual_x_minus2":2.338524},{"yb_etf":"SEMY","underlying":"SOXX","option_root":"2SOXL","sleeve_2x":"SOXL","expiry":"2026-05-26","strike_long":136.58,"strike_short":144.16,"qty":2750.0,"spot_2x":221.57,"moneyness_long_pct":-38.358,"moneyness_short_pct":-34.937,"iv_put_long":null,"iv_put_short":null,"spread_mid_market":null,"spread_mid_market_unavailable":true,"rv_30d_2x":1.467371,"rv_30d_underlying":null,"vrp_vol_2x":null,"rv_30d_source":"dashboard_1m","iv_source":"holdings_missing_chain","holdings_as_of":"2026-05-22","options_as_of":"2026-05-26T17:44:11.755291Z","days_to_exp":0,"iv_put_long_full":null,"iv_put_short_full":null,"iv_put_long_base":null,"iv_put_short_base":null,"iv_full_proxy":null,"iv_base_proxy":null,"rv_30d_2x_full":1.467371,"rv_30d_2x_base":1.638081,"vrp_vol_2x_full":null,"vrp_vol_2x_base":null,"event_implied_move_pct":null,"event_var_2x_annualized":null,"event_count_in_window":0,"event_types_in_window":[],"event_var_source":"none","event_calendar_stale":false,"put_spread_fair_event_aware":null,"put_spread_vrp_event_aware":null,"iv_underlying_implied":null,"iv_implied_weekly_move_2x_pct":20.6692,"iv_implied_weekly_move_underlying_pct":10.3346,"bs_put_spread_fair_diffusion":5e-06,"bs_put_spread_sigma_source":"rv_2x_full","expected_weekly_loss_pct_of_spot":0.0,"spread_breakeven_sigma_annual":null,"iv_minus_breakeven_sigma":null,"bs_delta_spread":1e-06,"bs_gamma_spread":-3e-07,"bs_vega_spread":-8.5e-05,"bs_theta_spread_per_day":6.2e-05,"bs_dollar_gamma_per_1pct_sleeve":-1e-06,"bs_dollar_gamma_per_1pct_underlying":-6e-06,"sleeve_diffusion_drag_annual":0.538294,"inverse_sleeve_drag_annual_x_minus2":1.614883},{"yb_etf":"SMYY","underlying":"SMCI","option_root":"2SMCX","sleeve_2x":"SMCX","expiry":"2026-05-26","strike_long":12.3,"strike_short":12.99,"qty":2041.0,"spot_2x":19.687,"moneyness_long_pct":-37.522,"moneyness_short_pct":-34.017,"iv_put_long":null,"iv_put_short":null,"spread_mid_market":null,"spread_mid_market_unavailable":true,"rv_30d_2x":1.883615,"rv_30d_underlying":null,"vrp_vol_2x":null,"rv_30d_source":"dashboard_1m","iv_source":"holdings_missing_chain","holdings_as_of":"2026-05-22","options_as_of":"2026-05-26T17:44:11.755291Z","days_to_exp":0,"iv_put_long_full":null,"iv_put_short_full":null,"iv_put_long_base":null,"iv_put_short_base":null,"iv_full_proxy":null,"iv_base_proxy":null,"rv_30d_2x_full":1.883615,"rv_30d_2x_base":1.431943,"vrp_vol_2x_full":null,"vrp_vol_2x_base":null,"event_implied_move_pct":null,"event_var_2x_annualized":null,"event_count_in_window":0,"event_types_in_window":[],"event_var_source":"none","event_calendar_stale":false,"put_spread_fair_event_aware":null,"put_spread_vrp_event_aware":null,"iv_underlying_implied":null,"iv_implied_weekly_move_2x_pct":26.5324,"iv_implied_weekly_move_underlying_pct":13.2662,"bs_put_spread_fair_diffusion":9.3e-05,"bs_put_spread_sigma_source":"rv_2x_full","expected_weekly_loss_pct_of_spot":0.0005,"spread_breakeven_sigma_annual":null,"iv_minus_breakeven_sigma":null,"bs_delta_spread":0.000154,"bs_gamma_spread":-0.00024527,"bs_vega_spread":-0.000711,"bs_theta_spread_per_day":0.000669,"bs_dollar_gamma_per_1pct_sleeve":-1e-05,"bs_dollar_gamma_per_1pct_underlying":-3.8e-05,"sleeve_diffusion_drag_annual":0.887001,"inverse_sleeve_drag_annual_x_minus2":2.661004},{"yb_etf":"TECY","underlying":"XLK","option_root":"2TECL","sleeve_2x":"TECL","expiry":"2026-05-26","strike_long":169.29,"strike_short":178.7,"qty":40.0,"spot_2x":222.625,"moneyness_long_pct":-23.957,"moneyness_short_pct":-19.73,"iv_put_long":null,"iv_put_short":null,"spread_mid_market":null,"spread_mid_market_unavailable":true,"rv_30d_2x":null,"rv_30d_underlying":null,"vrp_vol_2x":null,"rv_30d_source":null,"iv_source":"holdings_missing_chain","holdings_as_of":"2026-05-22","options_as_of":"2026-05-26T17:44:11.755291Z","days_to_exp":0,"iv_put_long_full":null,"iv_put_short_full":null,"iv_put_long_base":null,"iv_put_short_base":null,"iv_full_proxy":null,"iv_base_proxy":null,"rv_30d_2x_full":null,"rv_30d_2x_base":null,"vrp_vol_2x_full":null,"vrp_vol_2x_base":null,"event_implied_move_pct":null,"event_var_2x_annualized":null,"event_count_in_window":0,"event_types_in_window":[],"event_var_source":"none","event_calendar_stale":false,"put_spread_fair_event_aware":null,"put_spread_vrp_event_aware":null,"iv_underlying_implied":null,"iv_implied_weekly_move_2x_pct":null,"iv_implied_weekly_move_underlying_pct":null,"bs_put_spread_fair_diffusion":null,"bs_put_spread_sigma_source":null,"expected_weekly_loss_pct_of_spot":null,"spread_breakeven_sigma_annual":null,"iv_minus_breakeven_sigma":null,"bs_delta_spread":null,"bs_gamma_spread":null,"bs_vega_spread":null,"bs_theta_spread_per_day":null,"bs_dollar_gamma_per_1pct_sleeve":null,"bs_dollar_gamma_per_1pct_underlying":null,"sleeve_diffusion_drag_annual":null,"inverse_sleeve_drag_annual_x_minus2":null},{"yb_etf":"TMYY","underlying":"TSM","option_root":"2TSMU","sleeve_2x":"TSMU","expiry":"2026-05-26","strike_long":59.62,"strike_short":62.93,"qty":200.0,"spot_2x":71.34,"moneyness_long_pct":-16.428,"moneyness_short_pct":-11.789,"iv_put_long":null,"iv_put_short":null,"spread_mid_market":null,"spread_mid_market_unavailable":true,"rv_30d_2x":0.744704,"rv_30d_underlying":null,"vrp_vol_2x":null,"rv_30d_source":"dashboard_1m","iv_source":"holdings_missing_chain","holdings_as_of":"2026-05-22","options_as_of":"2026-05-26T17:44:11.755291Z","days_to_exp":0,"iv_put_long_full":null,"iv_put_short_full":null,"iv_put_long_base":null,"iv_put_short_base":null,"iv_full_proxy":null,"iv_base_proxy":null,"rv_30d_2x_full":0.744704,"rv_30d_2x_base":0.819216,"vrp_vol_2x_full":null,"vrp_vol_2x_base":null,"event_implied_move_pct":null,"event_var_2x_annualized":null,"event_count_in_window":0,"event_types_in_window":[],"event_var_source":"none","event_calendar_stale":false,"put_spread_fair_event_aware":null,"put_spread_vrp_event_aware":null,"iv_underlying_implied":null,"iv_implied_weekly_move_2x_pct":10.4898,"iv_implied_weekly_move_underlying_pct":5.2449,"bs_put_spread_fair_diffusion":0.003539,"bs_put_spread_sigma_source":"rv_2x_full","expected_weekly_loss_pct_of_spot":0.005,"spread_breakeven_sigma_annual":null,"iv_minus_breakeven_sigma":null,"bs_delta_spread":0.003399,"bs_gamma_spread":-0.0030348,"bs_vega_spread":-0.045644,"bs_theta_spread_per_day":0.016953,"bs_dollar_gamma_per_1pct_sleeve":-0.001545,"bs_dollar_gamma_per_1pct_underlying":-0.006178,"sleeve_diffusion_drag_annual":0.138646,"inverse_sleeve_drag_annual_x_minus2":0.415938},{"yb_etf":"TQQY","underlying":"QQQ","option_root":"2TQQQ","sleeve_2x":"TQQQ","expiry":"2026-05-26","strike_long":66.89,"strike_short":70.6,"qty":230.0,"spot_2x":81.25,"moneyness_long_pct":-17.674,"moneyness_short_pct":-13.108,"iv_put_long":null,"iv_put_short":null,"spread_mid_market":null,"spread_mid_market_unavailable":true,"rv_30d_2x":0.491705,"rv_30d_underlying":null,"vrp_vol_2x":null,"rv_30d_source":"dashboard_1m","iv_source":"holdings_missing_chain","holdings_as_of":"2026-05-22","options_as_of":"2026-05-26T17:44:11.755291Z","days_to_exp":0,"iv_put_long_full":null,"iv_put_short_full":null,"iv_put_long_base":null,"iv_put_short_base":null,"iv_full_proxy":null,"iv_base_proxy":null,"rv_30d_2x_full":0.491705,"rv_30d_2x_base":0.511756,"vrp_vol_2x_full":null,"vrp_vol_2x_base":null,"event_implied_move_pct":null,"event_var_2x_annualized":null,"event_count_in_window":0,"event_types_in_window":[],"event_var_source":"none","event_calendar_stale":false,"put_spread_fair_event_aware":null,"put_spread_vrp_event_aware":null,"iv_underlying_implied":null,"iv_implied_weekly_move_2x_pct":6.9261,"iv_implied_weekly_move_underlying_pct":3.4631,"bs_put_spread_fair_diffusion":1e-06,"bs_put_spread_sigma_source":"rv_2x_full","expected_weekly_loss_pct_of_spot":0.0,"spread_breakeven_sigma_annual":null,"iv_minus_breakeven_sigma":null,"bs_delta_spread":3e-06,"bs_gamma_spread":-4.91e-06,"bs_vega_spread":-6.3e-05,"bs_theta_spread_per_day":1.5e-05,"bs_dollar_gamma_per_1pct_sleeve":-3e-06,"bs_dollar_gamma_per_1pct_underlying":-1.3e-05,"sleeve_diffusion_drag_annual":0.060443,"inverse_sleeve_drag_annual_x_minus2":0.18133},{"yb_etf":"TSYY","underlying":"TSLA","option_root":"2TSLR","sleeve_2x":"TSLR","expiry":"2026-05-26","strike_long":21.79,"strike_short":23.0,"qty":25112.0,"spot_2x":26.65,"moneyness_long_pct":-18.236,"moneyness_short_pct":-13.696,"iv_put_long":null,"iv_put_short":null,"spread_mid_market":null,"spread_mid_market_unavailable":true,"rv_30d_2x":0.783779,"rv_30d_underlying":null,"vrp_vol_2x":null,"rv_30d_source":"dashboard_1m","iv_source":"holdings_missing_chain","holdings_as_of":"2026-05-22","options_as_of":"2026-05-26T17:44:11.755291Z","days_to_exp":0,"iv_put_long_full":null,"iv_put_short_full":null,"iv_put_long_base":null,"iv_put_short_base":null,"iv_full_proxy":null,"iv_base_proxy":null,"rv_30d_2x_full":0.783779,"rv_30d_2x_base":0.683784,"vrp_vol_2x_full":null,"vrp_vol_2x_base":null,"event_implied_move_pct":null,"event_var_2x_annualized":null,"event_count_in_window":0,"event_types_in_window":[],"event_var_source":"none","event_calendar_stale":false,"put_spread_fair_event_aware":null,"put_spread_vrp_event_aware":null,"iv_underlying_implied":null,"iv_implied_weekly_move_2x_pct":11.0402,"iv_implied_weekly_move_underlying_pct":5.5201,"bs_put_spread_fair_diffusion":0.000483,"bs_put_spread_sigma_source":"rv_2x_full","expected_weekly_loss_pct_of_spot":0.0018,"spread_breakeven_sigma_annual":null,"iv_minus_breakeven_sigma":null,"bs_delta_spread":0.00128,"bs_gamma_spread":-0.00318828,"bs_vega_spread":-0.007043,"bs_theta_spread_per_day":0.002754,"bs_dollar_gamma_per_1pct_sleeve":-0.000226,"bs_dollar_gamma_per_1pct_underlying":-0.000906,"sleeve_diffusion_drag_annual":0.153577,"inverse_sleeve_drag_annual_x_minus2":0.460732},{"yb_etf":"XBTY","underlying":"IBIT","option_root":"2BITX","sleeve_2x":"BITX","expiry":"2026-05-26","strike_long":16.55,"strike_short":17.47,"qty":3050.0,"spot_2x":17.81,"moneyness_long_pct":-7.075,"moneyness_short_pct":-1.909,"iv_put_long":null,"iv_put_short":null,"spread_mid_market":null,"spread_mid_market_unavailable":true,"rv_30d_2x":0.569925,"rv_30d_underlying":null,"vrp_vol_2x":null,"rv_30d_source":"dashboard_1m","iv_source":"holdings_missing_chain","holdings_as_of":"2026-05-22","options_as_of":"2026-05-26T18:55:41.732979Z","days_to_exp":0,"iv_put_long_full":null,"iv_put_short_full":null,"iv_put_long_base":null,"iv_put_short_base":null,"iv_full_proxy":null,"iv_base_proxy":null,"rv_30d_2x_full":0.569925,"rv_30d_2x_base":0.489542,"vrp_vol_2x_full":null,"vrp_vol_2x_base":null,"event_implied_move_pct":null,"event_var_2x_annualized":null,"event_count_in_window":0,"event_types_in_window":[],"event_var_source":"none","event_calendar_stale":false,"put_spread_fair_event_aware":null,"put_spread_vrp_event_aware":null,"iv_underlying_implied":null,"iv_implied_weekly_move_2x_pct":8.0279,"iv_implied_weekly_move_underlying_pct":4.014,"bs_put_spread_fair_diffusion":0.112708,"bs_put_spread_sigma_source":"rv_2x_full","expected_weekly_loss_pct_of_spot":0.6328,"spread_breakeven_sigma_annual":null,"iv_minus_breakeven_sigma":null,"bs_delta_spread":0.268489,"bs_gamma_spread":-0.45972921,"bs_vega_spread":-0.329797,"bs_theta_spread_per_day":0.093145,"bs_dollar_gamma_per_1pct_sleeve":-0.014582,"bs_dollar_gamma_per_1pct_underlying":-0.05833,"sleeve_diffusion_drag_annual":0.081204,"inverse_sleeve_drag_annual_x_minus2":0.243611},{"yb_etf":"XEY","underlying":"ETHA","option_root":"2ETHU","sleeve_2x":"ETHU","expiry":"2026-05-26","strike_long":19.88,"strike_short":20.99,"qty":350.0,"spot_2x":20.795,"moneyness_long_pct":-4.4,"moneyness_short_pct":0.938,"iv_put_long":null,"iv_put_short":null,"spread_mid_market":null,"spread_mid_market_unavailable":true,"rv_30d_2x":0.674466,"rv_30d_underlying":null,"vrp_vol_2x":null,"rv_30d_source":"dashboard_1m","iv_source":"holdings_missing_chain","holdings_as_of":"2026-05-22","options_as_of":"2026-05-26T18:55:41.732979Z","days_to_exp":0,"iv_put_long_full":null,"iv_put_short_full":null,"iv_put_long_base":null,"iv_put_short_base":null,"iv_full_proxy":null,"iv_base_proxy":null,"rv_30d_2x_full":0.674466,"rv_30d_2x_base":0.602299,"vrp_vol_2x_full":null,"vrp_vol_2x_base":null,"event_implied_move_pct":null,"event_var_2x_annualized":null,"event_count_in_window":0,"event_types_in_window":[],"event_var_source":"none","event_calendar_stale":false,"put_spread_fair_event_aware":null,"put_spread_vrp_event_aware":null,"iv_underlying_implied":null,"iv_implied_weekly_move_2x_pct":9.5005,"iv_implied_weekly_move_underlying_pct":4.7502,"bs_put_spread_fair_diffusion":0.394265,"bs_put_spread_sigma_source":"rv_2x_full","expected_weekly_loss_pct_of_spot":1.896,"spread_breakeven_sigma_annual":null,"iv_minus_breakeven_sigma":null,"bs_delta_spread":0.437973,"bs_gamma_spread":-0.19226162,"bs_vega_spread":-0.22252,"bs_theta_spread_per_day":0.07342,"bs_dollar_gamma_per_1pct_sleeve":-0.008314,"bs_dollar_gamma_per_1pct_underlying":-0.033256,"sleeve_diffusion_drag_annual":0.113726,"inverse_sleeve_drag_annual_x_minus2":0.341178},{"yb_etf":"YSPY","underlying":"SPY","option_root":"2SPXL","sleeve_2x":"SPXL","expiry":"2026-05-27","strike_long":241.79,"strike_short":255.22,"qty":170.0,"spot_2x":276.62,"moneyness_long_pct":-12.591,"moneyness_short_pct":-7.736,"iv_put_long":null,"iv_put_short":null,"spread_mid_market":null,"spread_mid_market_unavailable":true,"rv_30d_2x":0.307729,"rv_30d_underlying":null,"vrp_vol_2x":null,"rv_30d_source":"dashboard_1m","iv_source":"holdings_missing_chain","holdings_as_of":"2026-05-22","options_as_of":"2026-05-26T17:44:11.755291Z","days_to_exp":1,"iv_put_long_full":null,"iv_put_short_full":null,"iv_put_long_base":null,"iv_put_short_base":null,"iv_full_proxy":null,"iv_base_proxy":null,"rv_30d_2x_full":0.307729,"rv_30d_2x_base":0.293617,"vrp_vol_2x_full":null,"vrp_vol_2x_base":null,"event_implied_move_pct":null,"event_var_2x_annualized":null,"event_count_in_window":0,"event_types_in_window":[],"event_var_source":"none","event_calendar_stale":false,"put_spread_fair_event_aware":null,"put_spread_vrp_event_aware":null,"iv_underlying_implied":null,"iv_implied_weekly_move_2x_pct":4.3346,"iv_implied_weekly_move_underlying_pct":2.1673,"bs_put_spread_fair_diffusion":1.8e-05,"bs_put_spread_sigma_source":"rv_2x_full","expected_weekly_loss_pct_of_spot":0.0,"spread_breakeven_sigma_annual":null,"iv_minus_breakeven_sigma":null,"bs_delta_spread":1.5e-05,"bs_gamma_spread":-1.235e-05,"bs_vega_spread":-0.001154,"bs_theta_spread_per_day":0.000177,"bs_dollar_gamma_per_1pct_sleeve":-9.5e-05,"bs_dollar_gamma_per_1pct_underlying":-0.000378,"sleeve_diffusion_drag_annual":0.023674,"inverse_sleeve_drag_annual_x_minus2":0.071023}],"row_count":31}